livecheck_python/__init__.py
livecheck_python/livecheck_python.py
livecheck_python-1.0.2.dist-info/LICENSE
livecheck_python-1.0.2.dist-info/METADATA
livecheck_python-1.0.2.dist-info/WHEEL
livecheck_python-1.0.2.dist-info/top_level.txt
livecheck_python-1.0.2.dist-info/RECORD
