Metadata-Version: 2.1
Name: livecheck_python
Version: 1.0.2
Summary: Check Program Bugs Anywhere - Track Your Logs On-the-Go
Home-page: https://livecheck.dev
Author: Dinh Tuan Tran
Author-email: tuan.t.d@ieee.org
Project-URL: Documentation, https://livecheck.dev/help
Project-URL: Bug Reports, https://github.com/dinhtuantran/livecheck_python/issues
Project-URL: Source Code, https://github.com/dinhtuantran/livecheck_python
Keywords: debug,track,exception,log,plot,graph,smartphone,realtime,machine learning,deep learning,computer vision
Classifier: Development Status :: 5 - Production/Stable
Classifier: Intended Audience :: Developers
Classifier: Topic :: Software Development :: Build Tools
Classifier: Programming Language :: Python :: 3
Classifier: Programming Language :: Python :: 3.6
Classifier: Programming Language :: Python :: 3.7
Classifier: Programming Language :: Python :: 3.8
Classifier: Programming Language :: Python :: 3.9
Classifier: Programming Language :: Python :: 3 :: Only
Classifier: License :: OSI Approved :: MIT License
Classifier: Operating System :: OS Independent
Requires-Python: >=3.6.7
License-File: LICENSE
Requires-Dist: pytz
Requires-Dist: requests
